huscy/appointments/__init__.py
huscy/appointments/admin.py
huscy/appointments/apps.py
huscy/appointments/feed.py
huscy/appointments/filters.py
huscy/appointments/models.py
huscy/appointments/serializers.py
huscy/appointments/services.py
huscy/appointments/urls.py
huscy/appointments/validators.py
huscy/appointments/views.py
huscy/appointments/migrations/0001_initial.py
huscy/appointments/migrations/0002_auto_20200226_0735.py
huscy/appointments/migrations/0003_auto_20200226_0756.py
huscy/appointments/migrations/0004_auto_20211026_0424.py
huscy/appointments/migrations/__init__.py
huscy.appointments-1.3.3.dist-info/LICENSE
huscy.appointments-1.3.3.dist-info/METADATA
huscy.appointments-1.3.3.dist-info/WHEEL
huscy.appointments-1.3.3.dist-info/top_level.txt
huscy.appointments-1.3.3.dist-info/RECORD
